cv2/LICENSE-3RD-PARTY.txt
cv2/LICENSE.txt
cv2/__init__.py
cv2/__init__.pyi
cv2/config-3.9.py
cv2/config-3.py
cv2/config.py
cv2/cv2.pyd
cv2/load_config_py2.py
cv2/load_config_py3.py
cv2/opencv_videoio_ffmpeg460_64.dll
cv2/py.typed
cv2/version.py
cv2/data/__init__.py
cv2/gapi/__init__.py
cv2/mat_wrapper/__init__.py
cv2/misc/__init__.py
cv2/misc/version.py
cv2/typing/__init__.py
cv2/utils/__init__.py
opencv_cuda_v12.6-4.12.0.dist-info/METADATA
opencv_cuda_v12.6-4.12.0.dist-info/WHEEL
opencv_cuda_v12.6-4.12.0.dist-info/top_level.txt
opencv_cuda_v12.6-4.12.0.dist-info/RECORD
